cluster_estimator.py
compute_shingles.py
fdedup_local_ray.py
fdedup_s3_ray.py
fdedup_support.py
fdedup_transform_ray.py
dpk_fdedup_transform_ray-0.2.0.dist-info/METADATA
dpk_fdedup_transform_ray-0.2.0.dist-info/WHEEL
dpk_fdedup_transform_ray-0.2.0.dist-info/top_level.txt
dpk_fdedup_transform_ray-0.2.0.dist-info/RECORD
