Metadata-Version: 2.1
Name: dpk_fdedup_transform_ray
Version: 0.2.0
Summary: fdedup Ray Transform
Author-email: David Wood <dawood@us.ibm.com>, Boris Lublinsky <blublinsky@ibm.com>
License: Apache-2.0
Requires-Python: >=3.10
Requires-Dist: data-prep-toolkit-ray ==0.2.0
Requires-Dist: mmh3 ==4.1.0
Requires-Dist: xxhash ==3.4.1
Requires-Dist: tqdm ==4.66.3
Requires-Dist: scipy ==1.12.0
Provides-Extra: dev
Requires-Dist: twine ; extra == 'dev'
Requires-Dist: pytest >=7.3.2 ; extra == 'dev'
Requires-Dist: pytest-dotenv >=0.5.2 ; extra == 'dev'
Requires-Dist: pytest-env >=1.0.0 ; extra == 'dev'
Requires-Dist: pre-commit >=3.3.2 ; extra == 'dev'
Requires-Dist: pytest-cov >=4.1.0 ; extra == 'dev'
Requires-Dist: pytest-mock >=3.10.0 ; extra == 'dev'
Requires-Dist: moto ==5.0.5 ; extra == 'dev'
Requires-Dist: markupsafe ==2.0.1 ; extra == 'dev'
